<Properties StartupConfiguration="{55CEFEE5-DB37-49F7-8512-77785319A1E2}|Default">
  <MonoDevelop.Ide.ItemProperties.TicketsBooking.APIs PreferredExecutionTarget="/Applications/Google Chrome.app" />
  <MonoDevelop.Ide.Workbench ActiveDocument="TicketsBooking.UnitTest/RepoLayerTesting/AdminTests/AdminAuthTests.cs">
    <Files>
      <File FileName="TicketsBooking.UnitTest/RepoLayerTesting/AdminTests/AdminAuthTests.cs" Line="12" Column="6" />
      <File FileName="TicketsBooking.Infrastructure/Repos/AdminRepo.cs" Line="10" Column="1" />
      <File FileName="TicketsBooking.Infrastructure/Persistence/Seeders/EventsSeeder.cs" Line="22" Column="1" />
      <File FileName="TicketsBooking.Infrastructure/Persistence/AppDbContext.cs" Line="8" Column="30" />
    </Files>
    <Pads>
      <Pad Id="ProjectPad">
        <State name="__root__">
          <Node name="TicketsBooking" expanded="True">
            <Node name="TicketsBooking.APIs" expanded="True">
              <Node name="Controllers" expanded="True" />
              <Node name="Setups" expanded="True">
                <Node name="Bases" expanded="True" />
              </Node>
            </Node>
            <Node name="TicketsBooking.Application" expanded="True">
              <Node name="Components" expanded="True">
                <Node name="Admins" expanded="True" />
                <Node name="Authentication" expanded="True" />
                <Node name="EventProviders" expanded="True" />
              </Node>
            </Node>
            <Node name="TicketsBooking.Crosscut" expanded="True">
              <Node name="Constants" expanded="True" />
            </Node>
            <Node name="TicketsBooking.Domain" expanded="True">
              <Node name="Entities" expanded="True" />
            </Node>
            <Node name="TicketsBooking.Infrastructure" expanded="True">
              <Node name="Persistence" expanded="True">
                <Node name="Configurations" expanded="True" />
                <Node name="Seeders" expanded="True" />
              </Node>
              <Node name="Repos" expanded="True" />
            </Node>
            <Node name="TicketsBooking.UnitTest" expanded="True">
              <Node name="RepoLayerTesting" expanded="True">
                <Node name="AdminTests" expanded="True">
                  <Node name="AdminAuthTests.cs" selected="True" />
                </Node>
              </Node>
              <Node name="ServideLayerTesting" expanded="True">
                <Node name="EventProviderTests" expanded="True" />
              </Node>
            </Node>
          </Node>
        </State>
      </Pad>
      <Pad Id="MonoDevelop.UnitTesting.TestPad">
        <State name="__root__">
          <Node name="TicketsBooking" expanded="True" selected="True">
            <Node name="TicketsBooking.UnitTest" expanded="True" />
          </Node>
        </State>
      </Pad>
    </Pads>
  </MonoDevelop.Ide.Workbench>
  <MonoDevelop.Ide.DebuggingService.PinnedWatches />
  <MonoDevelop.Ide.Workspace ActiveConfiguration="Debug" />
  <MonoDevelop.Ide.DebuggingService.Breakpoints>
    <BreakpointStore />
  </MonoDevelop.Ide.DebuggingService.Breakpoints>
  <MultiItemStartupConfigurations />
</Properties>